{
  "version": "1.1.0",
  "flags": {},
  "shapes": [
    {
      "direction": 0.060000000000000005,
      "label": "left",
      "text": "",
      "points": [
        [
          336.012143225286,
          1.5751933473299142
        ],
        [
          394.82014388489205,
          5.107913669064764
        ],
        [
          366.5119913550445,
          476.3441568568571
        ],
        [
          307.70399069543856,
          472.8114365351223
        ]
      ],
      "group_id": null,
      "shape_type": "rotation",
      "flags": {}
    }
  ],
  "imagePath": "..\\images\\107.png",
  "imageData": null,
  "imageHeight": 480,
  "imageWidth": 640,
  "text": ""
}